keywordrich/__init__.py
keywordrich/keywordrich.py
keywordrich-0.0.2.data/scripts/keywordrich.py
keywordrich-0.0.2.dist-info/METADATA
keywordrich-0.0.2.dist-info/WHEEL
keywordrich-0.0.2.dist-info/entry_points.txt
keywordrich-0.0.2.dist-info/top_level.txt
keywordrich-0.0.2.dist-info/RECORD
