Metadata-Version: 2.1
Name: keywordrich
Version: 0.0.2
Summary: keywordrich
Author: feng wang
Author-email: Sysiphus6@2925.com
License: MIT
Keywords: python,keyword rich,ai
Classifier: Development Status :: 3 - Alpha
Classifier: Intended Audience :: Developers
Classifier: Programming Language :: Python :: 3
Classifier: Operating System :: Microsoft :: Windows
Requires-Dist: langchain
Requires-Dist: langchain-openai
